scrapy_spider_metadata/__init__.py
scrapy_spider_metadata/_metadata.py
scrapy_spider_metadata/_params.py
scrapy_spider_metadata/_utils.py
scrapy_spider_metadata/py.typed
scrapy_spider_metadata-0.2.0.dist-info/LICENSE
scrapy_spider_metadata-0.2.0.dist-info/METADATA
scrapy_spider_metadata-0.2.0.dist-info/WHEEL
scrapy_spider_metadata-0.2.0.dist-info/top_level.txt
scrapy_spider_metadata-0.2.0.dist-info/RECORD
