Metadata-Version: 2.1
Name: scrapy-spider-metadata
Version: 0.2.0
Summary: Utilities to extend Scrapy spiders with usable metadata.
Author-email: Zyte Group Ltd <info@zyte.com>
License: The MIT License (MIT)
Project-URL: Source, https://github.com/scrapy-plugins/scrapy-spider-metadata
Classifier: Development Status :: 3 - Alpha
Classifier: Intended Audience :: Developers
Classifier: License :: OSI Approved :: BSD License
Classifier: Natural Language :: English
Classifier: Operating System :: OS Independent
Classifier: Programming Language :: Python :: 3
Classifier: Programming Language :: Python :: 3.8
Classifier: Programming Language :: Python :: 3.9
Classifier: Programming Language :: Python :: 3.10
Classifier: Programming Language :: Python :: 3.11
Classifier: Programming Language :: Python :: 3.12
Classifier: Programming Language :: Python :: Implementation :: CPython
Classifier: Programming Language :: Python :: Implementation :: PyPy
Requires-Python: >=3.8
License-File: LICENSE
Requires-Dist: packaging >=14.1
Requires-Dist: pydantic >=1.9
Requires-Dist: scrapy >=1.0.0
